tvimspr.py
tvimspr-0.1.dist-info/METADATA
tvimspr-0.1.dist-info/WHEEL
tvimspr-0.1.dist-info/top_level.txt
tvimspr-0.1.dist-info/RECORD
