Metadata-Version: 2.1
Name: tvimspr
Version: 0.1
Requires-Dist: pyperclip
